sandboxcreator/__init__.py
sandboxcreator/creator.py
sandboxcreator/manager.py
sandboxcreator/ansible_generator/__init__.py
sandboxcreator/ansible_generator/preconfig.py
sandboxcreator/ansible_generator/provisioning.py
sandboxcreator/ansible_generator/routes.py
sandboxcreator/ansible_generator/vars.py
sandboxcreator/commands/__init__.py
sandboxcreator/commands/command.py
sandboxcreator/commands/command_attributes.py
sandboxcreator/hw_resources/__init__.py
sandboxcreator/hw_resources/cpu.py
sandboxcreator/hw_resources/disc.py
sandboxcreator/hw_resources/memory.py
sandboxcreator/hw_resources/resource_checker.py
sandboxcreator/input_parser/__init__.py
sandboxcreator/input_parser/sandbox.py
sandboxcreator/input_parser/topology_parser.py
sandboxcreator/io/__init__.py
sandboxcreator/io/reader.py
sandboxcreator/io/writer.py
sandboxcreator/resources/conf/configuration.yml
sandboxcreator/resources/conf/flavors.yml
sandboxcreator/resources/files/playbook.yml
sandboxcreator/resources/files/user_playbook.yml
sandboxcreator/resources/templates/vagrantfile.j2
sandboxcreator/scripts/__init__.py
sandboxcreator/scripts/create.py
sandboxcreator/scripts/manage.py
sandboxcreator/vagrant_generator/__init__.py
sandboxcreator/vagrant_generator/vagrantfile.py
sandboxcreator-3.1.0.dist-info/LICENSE
sandboxcreator-3.1.0.dist-info/METADATA
sandboxcreator-3.1.0.dist-info/WHEEL
sandboxcreator-3.1.0.dist-info/dependency_links.txt
sandboxcreator-3.1.0.dist-info/entry_points.txt
sandboxcreator-3.1.0.dist-info/top_level.txt
sandboxcreator-3.1.0.dist-info/RECORD
