Metadata-Version: 2.1
Name: sandboxcreator
Version: 3.1.0
Summary: Local virtual lab creation
Home-page: https://gitlab.ics.muni.cz/muni-kypo-csc/cyber-sandbox-creator
Author: Attila Farkas, Jana Ziková, Kamil Andoniadis
Author-email: farkas@mail.muni.cz
Project-URL: Bug Tracker, https://gitlab.ics.muni.cz/muni-kypo-csc/cyber-sandbox-creator/-/issues
Project-URL: Documentation, https://gitlab.ics.muni.cz/muni-kypo-csc/cyber-sandbox-creator/-/wikis/home
Classifier: Programming Language :: Python :: 3
Classifier: Programming Language :: Python :: 3.7
Classifier: Programming Language :: Python :: 3.8
Classifier: Programming Language :: Python :: 3.9
Classifier: Programming Language :: Python :: 3.10
Classifier: License :: OSI Approved :: MIT License
Classifier: Operating System :: OS Independent
Requires-Python: >=3.7
License-File: LICENSE
Requires-Dist: Jinja2 (>=2.11.3)
Requires-Dist: PyYAML (>=5.4)
Requires-Dist: psutil (>=5.6.7)
Requires-Dist: netaddr (>=0.8)
Requires-Dist: kypo-topology-definition (==0.5.1)
